README.md
setup.py
connectwrap/__init__.py
connectwrap/connectwrap.py
connectwrap/utils.py
connectwrap.egg-info/PKG-INFO
connectwrap.egg-info/SOURCES.txt
connectwrap.egg-info/dependency_links.txt
connectwrap.egg-info/top_level.txt