Metadata-Version: 2.1
Name: connectwrap
Version: 1.1.6
Summary: Python package made to manage, display & parse data from SQLite file databases.
Home-page: https://github.com/CodeConfidant/connectwrap-sqlite3
Author: Drew Hainer
Author-email: codeconfidant@gmail.com
License: MIT
Platform: Windows
Platform: Linux
Requires-Python: >=3.6
